mocap_skeletal/__init__.py
mocap_skeletal/axengine_1728043065_1977226932.py
mocap_skeletal/operations/__init__.py
mocap_skeletal/skeletal_optimisation/__init__.py
mocap_skeletal/skeletal_optimisation/losses.py
mocap_skeletal/skeletal_optimisation/main_skeleton_opt.py
mocap_skeletal/skeletal_optimisation/optimisers.py
mocap_skeletal/skeletal_optimisation/skeletons.py
mocap_skeletal/skeletal_optimisation/tests/__init__.py
mocap_skeletal/skeletal_optimisation/tests/lidar_data.py
mocap_skeletal/skeletal_optimisation/tests/tpose.py
mocap_skeletal/skeletal_optimisation/triangulated_3dpose.py
mocap_skeletal/skeletal_optimisation/utils.py
mocap_skeletal/triangulation/__init__.py
mocap_skeletal/triangulation/common_triangulate.py
mocap_skeletal/triangulation/epipolar_error_evaluation.py
mocap_skeletal/triangulation/human_bone_lengths.py
mocap_skeletal/triangulation/prep_triangulation_data.py
mocap_skeletal/triangulation/ransac_triangulate.py
mocap_skeletal/triangulation/triangulate.py
mocap_skeletal/triangulation/triangulation_evaluation.py
mocap_skeletal/triangulation/vol_triangulation/__init__.py
mocap_skeletal/triangulation/vol_triangulation/img.py
mocap_skeletal/triangulation/vol_triangulation/loss.py
mocap_skeletal/triangulation/vol_triangulation/multiview.py
mocap_skeletal/triangulation/vol_triangulation/op.py
mocap_skeletal/triangulation/vol_triangulation/pose_resnet.py
mocap_skeletal/triangulation/vol_triangulation/triangulation.py
mocap_skeletal/triangulation/vol_triangulation/v2v.py
mocap_skeletal/triangulation/vol_triangulation/vis.py
mocap_skeletal/triangulation/vol_triangulation/volumetric.py
mocap_skeletal-2.1.1.dist-info/METADATA
mocap_skeletal-2.1.1.dist-info/WHEEL
mocap_skeletal-2.1.1.dist-info/RECORD
