Metadata-Version: 2.1
Name: mocap-skeletal
Version: 2.1.1
Summary: 
Keywords: MotionOps,Moveai
Author: move.ai
Author-email: info@move.ai
Requires-Python: >=3.10,<4.0
Classifier: Programming Language :: Python :: 3
Classifier: Programming Language :: Python :: 3.10
Classifier: Programming Language :: Python :: 3.11
Classifier: Programming Language :: Python :: 3.12
Requires-Dist: imageio (>=2.31.1,<3.0.0)
Requires-Dist: mocap-base (>=2.0.1,<3.0.0)
Requires-Dist: tqdm (>=4.65.0,<5.0.0)
